nd2reader/__init__.py
nd2reader/artificial.py
nd2reader/common.py
nd2reader/common_raw_metadata.py
nd2reader/exceptions.py
nd2reader/label_map.py
nd2reader/legacy.py
nd2reader/parser.py
nd2reader/raw_metadata.py
nd2reader/reader.py
nd2reader/stitched.py
nd2reader-3.3.1.dist-info/COPYING
nd2reader-3.3.1.dist-info/LICENSE
nd2reader-3.3.1.dist-info/METADATA
nd2reader-3.3.1.dist-info/WHEEL
nd2reader-3.3.1.dist-info/top_level.txt
nd2reader-3.3.1.dist-info/RECORD
