Metadata-Version: 2.1
Name: nd2reader
Version: 3.3.1
Summary: A tool for reading ND2 files produced by NIS Elements
Home-page: https://open-science-tools.github.io/nd2reader/
Download-URL: https://github.com/rbnvrw/nd2reader/tarball/3.3.1
Author: Ruben Verweij
Author-email: ruben@kedara.nl
Keywords: nd2,nikon,microscopy,NIS Elements
Classifier: Development Status :: 5 - Production/Stable
Classifier: Intended Audience :: Science/Research
Classifier: License :: Freely Distributable
Classifier: License :: OSI Approved :: GNU General Public License v3 or later (GPLv3+)
Classifier: Operating System :: POSIX :: Linux
Classifier: Programming Language :: Python :: 2.7
Classifier: Programming Language :: Python :: 3.4
Classifier: Topic :: Scientific/Engineering
Requires-Python: >=3.6
License-File: LICENSE
License-File: COPYING
Requires-Dist: numpy>=1.14
Requires-Dist: six>=1.4
Requires-Dist: xmltodict>=0.9.2
Requires-Dist: pims>=0.3.0
